harbor_client/__init__.py
harbor_client/api/__init__.py
harbor_client/api/artifact_api.py
harbor_client/api/auditlog_api.py
harbor_client/api/configure_api.py
harbor_client/api/gc_api.py
harbor_client/api/health_api.py
harbor_client/api/icon_api.py
harbor_client/api/immutable_api.py
harbor_client/api/jobservice_api.py
harbor_client/api/label_api.py
harbor_client/api/ldap_api.py
harbor_client/api/member_api.py
harbor_client/api/oidc_api.py
harbor_client/api/permissions_api.py
harbor_client/api/ping_api.py
harbor_client/api/preheat_api.py
harbor_client/api/project_api.py
harbor_client/api/project_metadata_api.py
harbor_client/api/purge_api.py
harbor_client/api/quota_api.py
harbor_client/api/registry_api.py
harbor_client/api/replication_api.py
harbor_client/api/repository_api.py
harbor_client/api/retention_api.py
harbor_client/api/robot_api.py
harbor_client/api/robotv1_api.py
harbor_client/api/scan_all_api.py
harbor_client/api/scan_api.py
harbor_client/api/scan_data_export_api.py
harbor_client/api/scanner_api.py
harbor_client/api/schedule_api.py
harbor_client/api/search_api.py
harbor_client/api/securityhub_api.py
harbor_client/api/statistic_api.py
harbor_client/api/system_cve_allowlist_api.py
harbor_client/api/systeminfo_api.py
harbor_client/api/user_api.py
harbor_client/api/usergroup_api.py
harbor_client/api/webhook_api.py
harbor_client/api/webhookjob_api.py
harbor_client/api_client.py
harbor_client/configuration.py
harbor_client/models/__init__.py
harbor_client/models/access.py
harbor_client/models/accessory.py
harbor_client/models/action_request.py
harbor_client/models/addition_link.py
harbor_client/models/addition_links.py
harbor_client/models/annotations.py
harbor_client/models/artifact.py
harbor_client/models/audit_log.py
harbor_client/models/authproxy_setting.py
harbor_client/models/body.py
harbor_client/models/body1.py
harbor_client/models/bool_config_item.py
harbor_client/models/component_health_status.py
harbor_client/models/configurations.py
harbor_api_client-2.12.2.dist-info/METADATA
harbor_api_client-2.12.2.dist-info/WHEEL
harbor_api_client-2.12.2.dist-info/RECORD
