Metadata-Version: 2.1
Name: harbor-api-client
Version: 2.12.2
Summary: Client for the Harbor API
Home-page: https://container-registry.com
License: Apache-2.0
Keywords: Swagger,Harbor API
Author: Vadim Bauer
Author-email: vb@container-registry.com
Requires-Python: >=3.4
Classifier: License :: OSI Approved :: Apache Software License
Classifier: Programming Language :: Python :: 3
Classifier: Programming Language :: Python :: 3.4
Classifier: Programming Language :: Python :: 3.5
Classifier: Programming Language :: Python :: 3.6
Classifier: Programming Language :: Python :: 3.7
Classifier: Programming Language :: Python :: 3.8
Classifier: Programming Language :: Python :: 3.9
Classifier: Programming Language :: Python :: 3.10
Classifier: Programming Language :: Python :: 3.11
Classifier: Programming Language :: Python :: 3.12
Requires-Dist: certifi (>=2025.1.21,<2026.0.0)
Requires-Dist: python_dateutil (>=2.8.1,<3.0.0)
Requires-Dist: six (>=1.10,<2.0)
Requires-Dist: urllib3 (>=2.2.3,<3.0.0)
Project-URL: Documentation, https://container-registry.com/docs/
